CodeKeeper/__init__.py
CodeKeeper/interface.py
codekeeper-1.1.1.dist-info/METADATA
codekeeper-1.1.1.dist-info/WHEEL
codekeeper-1.1.1.dist-info/top_level.txt
codekeeper-1.1.1.dist-info/RECORD
