Metadata-Version: 2.1
Name: codekeeper
Version: 1.1.1
Summary: An interface for importing your code from AWS S3
Home-page: https://github.com/mwatrak1/CodeKeeper
Author: Michal Watrak
Author-email: mwatrak1@protonmail.com
License: MIT
Platform: UNKNOWN
Classifier: License :: OSI Approved :: MIT License
Classifier: Programming Language :: Python :: 3
Classifier: Programming Language :: Python :: 3.8
Requires-Dist: boto3
